dropboxdrivefs/__init__.py
dropboxdrivefs/core.py
dropboxdrivefs-1.3.dist-info/LICENSE
dropboxdrivefs-1.3.dist-info/METADATA
dropboxdrivefs-1.3.dist-info/WHEEL
dropboxdrivefs-1.3.dist-info/top_level.txt
dropboxdrivefs-1.3.dist-info/RECORD
