Metadata-Version: 2.1
Name: dropboxdrivefs
Version: 1.3
Summary: Dropbox implementation for fsspec module
Home-page: UNKNOWN
Author: Marine Chaput
Author-email: marine.chaput@hotmail.fr
License: BSD
Platform: UNKNOWN
Classifier: Development Status :: 4 - Beta
Classifier: Intended Audience :: Developers
Classifier: License :: OSI Approved :: BSD License
Classifier: Operating System :: OS Independent
Classifier: Programming Language :: Python :: 3.5
Classifier: Programming Language :: Python :: 3.6
Classifier: Programming Language :: Python :: 3.7
Requires-Python: >=3.5
Requires-Dist: fsspec
Requires-Dist: requests
Requires-Dist: dropbox
